{
    "url": "https://elections.democracyclub.org.uk/api/organisations/local-authority/NEC/1974-04-01/",
    "official_identifier": "NEC",
    "organisation_type": "local-authority",
    "organisation_subtype": "NMD",
    "official_name": "Newcastle-under-Lyme Borough Council",
    "common_name": "Newcastle-under-Lyme",
    "slug": "newcastle-under-lyme",
    "territory_code": "ENG",
    "election_name": "Newcastle-under-Lyme local election",
    "start_date": "1974-04-01",
    "end_date": null,
    "created": "1974-04-01T00:00:00Z"
}