{
    "everyelectiion_data": {
        "common_name": "Dorset",
        "created": "1997-04-01T00:00:00Z",
        "election_name": "Dorset local election",
        "end_date": "2019-03-31",
        "official_identifier": "DOR",
        "official_name": "Dorset County Council",
        "organisation_subtype": "CTY",
        "organisation_type": "local-authority",
        "slug": "dorset",
        "start_date": "1997-04-01",
        "territory_code": "ENG",
        "url": "http://elections.democracyclub.org.uk/api/organisations/local-authority/DOR/1997-04-01/"
    },
    "services": {
        "councillors": {
            "base_url": "https://dorset.moderngov.co.uk/",
            "cms_type": "ModernGov"
        }
    }
}