{
    "url": "https://elections.democracyclub.org.uk/api/organisations/local-authority/BRM/1974-04-01/",
    "official_identifier": "BRM",
    "organisation_type": "local-authority",
    "organisation_subtype": "NMD",
    "official_name": "Bromsgrove District Council",
    "common_name": "Bromsgrove",
    "slug": "bromsgrove",
    "territory_code": "ENG",
    "election_name": "Bromsgrove local election",
    "start_date": "1974-04-01",
    "end_date": null,
    "created": "1974-04-01T00:00:00Z"
}