{
    "everyelectiion_data": {
        "common_name": "Barrow-in-Furness",
        "created": "1974-04-01T00:00:00Z",
        "election_name": "Barrow-in-Furness local election",
        "end_date": "2023-03-31",
        "official_identifier": "BAR",
        "official_name": "Barrow-in-Furness Borough Council",
        "organisation_subtype": "NMD",
        "organisation_type": "local-authority",
        "slug": "barrow-in-furness",
        "start_date": "1974-04-01",
        "territory_code": "ENG",
        "url": "http://elections.democracyclub.org.uk/api/organisations/local-authority/BAR/1974-04-01/"
    },
    "services": {
        "councillors": {
            "base_url": "https://democracy.barrowbc.gov.uk",
            "cms_type": "ModernGov"
        }
    }
}