{
    "everyelectiion_data": {
        "common_name": "Malvern Hills",
        "created": "1998-04-01T00:00:00Z",
        "election_name": "Malvern Hills local election",
        "official_identifier": "MAV",
        "official_name": "Malvern Hills District Council",
        "organisation_subtype": "NMD",
        "organisation_type": "local-authority",
        "slug": "malvern-hills",
        "start_date": "1998-04-01",
        "territory_code": "ENG",
        "url": "http://elections.democracyclub.org.uk/api/organisations/local-authority/MAV/1998-04-01/"
    },
    "services": {
        "councillors": {
            "base_url": "http://moderngov.malvernhills.gov.uk",
            "cms_type": "ModernGov"
        }
    }
}